extras/__init__.py
extras/divide.py
extras/multiply.py
simple_math_package_by_rshaw-0.0.1.dist-info/METADATA
simple_math_package_by_rshaw-0.0.1.dist-info/WHEEL
simple_math_package_by_rshaw-0.0.1.dist-info/top_level.txt
simple_math_package_by_rshaw-0.0.1.dist-info/RECORD
