Metadata-Version: 2.1
Name: simple-math-package-by-rshaw
Version: 0.0.1
Summary: My first Python package
Author: Rakesh Shaw
Author-email: rakesh.shaw018@gmail.com
Keywords: python,first package
Classifier: Development Status :: 3 - Alpha
Classifier: Intended Audience :: Education
Classifier: Programming Language :: Python :: 2
Classifier: Programming Language :: Python :: 3
Classifier: Operating System :: MacOS :: MacOS X
Classifier: Operating System :: Microsoft :: Windows
